[
  {
    "name": "Bug",
    "src": "/Bug.jpg",
    "type": "image/jpg"
  },
  {
    "name": "Dark",
    "src": "/Dark.jpg",
    "type": "image/jpg"
  },
  {
    "name": "Dragon",
    "src": "/Dragon.jpg",
    "type": "image/jpg"
  },
  {
    "name": "Electric",
    "src": "/Electric.jpg",
    "type": "image/jpg"
  },
  {
    "name": "Fairy",
    "src": "/Fairy.jpg",
    "type": "image/jpg"
  },
  {
    "name": "Fighting",
    "src": "/Fighting.jpg",
    "type": "image/jpg"
  },
  {
    "name": "Fire",
    "src": "/Fire.jpg",
    "type": "image/jpg"
  },
  {
    "name": "Flying",
    "src": "/Flying.jpg",
    "type": "image/jpg"
  },
  {
    "name": "Ghost",
    "src": "/Ghost.jpg",
    "type": "image/jpg"
  },
  {
    "name": "Grass",
    "src": "/Grass.jpg",
    "type": "image/jpg"
  },
  {
    "name": "Ground",
    "src": "/Ground.jpg",
    "type": "image/jpg"
  },
  {
    "name": "Ice",
    "src": "/Ice.jpg",
    "type": "image/jpg"
  },
  {
    "name": "Normal",
    "src": "/Normal.jpg",
    "type": "image/jpg"
  },
  {
    "name": "Poison",
    "src": "/Poison.jpg",
    "type": "image/jpg"
  },
  {
    "name": "Psychic",
    "src": "/Psychic.jpg",
    "type": "image/jpg"
  },
  {
    "name": "Rock",
    "src": "/Rock.jpg",
    "type": "image/jpg"
  },
  {
    "name": "Shadow",
    "src": "/Shadow.jpg",
    "type": "image/jpg"
  },
  {
    "name": "Steel",
    "src": "/Steel.jpg",
    "type": "image/jpg"
  },
  {
    "name": "Unknown",
    "src": "/Unknown.jpg",
    "type": "image/jpg"
  },
  {
    "name": "Water",
    "src": "/Water.jpg",
    "type": "image/jpg"
  }
]
